README.md
setup.py
str2_md5/__init__.py
str2_md5/str2_md5.py
str2_md5.egg-info/PKG-INFO
str2_md5.egg-info/SOURCES.txt
str2_md5.egg-info/dependency_links.txt
str2_md5.egg-info/top_level.txt